{
  "env": {
    "node": true,
    "browser": true,
    "es2021": true,
    "commonjs": true,
    "es6": true
  },
  "extends": [
    "eslint:recommended",
    "plugin:@typescript-eslint/recommended"
  ],
  "parser": "@typescript-eslint/parser",
  "parserOptions": {
    "ecmaVersion": 12
  },
  "plugins": [
    "@typescript-eslint",
    "typescript",
    "jsdoc"
  ],
  "rules": {
    "eqeqeq": "error",
    "typescript/class-name-casing": "error",
    "typescript/no-type-alias": "error",
    "no-eval": "error",
    "no-new-func": "error",
    "no-self-compare": "error",
    "no-var": "error",
    "no-mixed-requires": "off",
    "no-use-before-define": "error",
    "space-before-blocks": "error",
    "indent": [
      "error",
      2
    ],
    "linebreak-style": [
      "error",
      "unix"
    ],
    "quotes": [
      "error",
      "single"
    ],
    "semi": [
      "error",
      "never"
    ],
    "strict": [
      2,
      "never"
    ],
    // Require statement not part of import
    // statement.eslint@typescript-eslint/no-var-requires
    "@typescript-eslint/no-var-requires": 0
    // "valid-jsdoc": [
    //   2,
    //   {
    //     "prefer": {
    //       "return": "return"
    //     }
    //     // "js/ts.implicitProjectConfig.checkJs": true
    //   }
    // ],
    // "jsdoc/check-types": 1, // Recommended
    // "jsdoc/check-values": 1 // Recommended
  }
}